archivy_hn/__init__.py
archivy_pocket/__init__.py
firefox/__init__.py
archivy_firefox-0.1.0.dist-info/LICENSE
archivy_firefox-0.1.0.dist-info/METADATA
archivy_firefox-0.1.0.dist-info/WHEEL
archivy_firefox-0.1.0.dist-info/entry_points.txt
archivy_firefox-0.1.0.dist-info/top_level.txt
archivy_firefox-0.1.0.dist-info/RECORD
