Metadata-Version: 2.1
Name: archivy-firefox
Version: 0.1.0
Summary: Archivy extension to download Firefox bookmarks into Archivy.
Home-page: UNKNOWN
Author: Uzay-G
Author-email: halcyon@disroot.org
License: UNKNOWN
Platform: UNKNOWN
Classifier: Programming Language :: Python :: 3
Classifier: License :: OSI Approved :: MIT License
License-File: LICENSE
Requires-Dist: archivy
Requires-Dist: click
